fastconfig/__init__.py
fastconfig/config.py
fastconfig/exception.py
fastconfig/internals/loader.py
fastconfig/internals/type_checker.py
fastconfig/internals/validator.py
fastconfig-0.2.0.dist-info/LICENSE
fastconfig-0.2.0.dist-info/METADATA
fastconfig-0.2.0.dist-info/WHEEL
fastconfig-0.2.0.dist-info/RECORD
