Metadata-Version: 2.1
Name: fastconfig
Version: 0.2.0
Summary: A lightweight way to find the project root and load config
Home-page: https://github.com/kyoto7250
License: MIT
Author: kyoto7250
Author-email: kyoto7250@aol.com
Requires-Python: >=3.8,<4.0
Classifier: License :: OSI Approved :: MIT License
Classifier: Programming Language :: Python :: 3
Classifier: Programming Language :: Python :: 3.8
Classifier: Programming Language :: Python :: 3.9
Classifier: Programming Language :: Python :: 3.10
Classifier: Programming Language :: Python :: 3.11
Requires-Dist: toml (>=0.10.0,<0.11.0)
Project-URL: Repository, https://github.com/kyoto7250/fastconfig
